reportportal_listener/__init__.py
reportportal_listener/message.py
reportportal_listener/model.py
reportportal_listener/report.py
reportportal_listener/report_modifier.py
reportportal_listener/service.py
reportportal_listener/variables.py
robotframework_reportportal_ng-2.0.0.dist-info/LICENSE
robotframework_reportportal_ng-2.0.0.dist-info/METADATA
robotframework_reportportal_ng-2.0.0.dist-info/WHEEL
robotframework_reportportal_ng-2.0.0.dist-info/top_level.txt
robotframework_reportportal_ng-2.0.0.dist-info/RECORD
