Metadata-Version: 2.1
Name: robotframework-reportportal-ng
Version: 2.0.0
Summary: A Robot Framework Report Portal Listener
Home-page: https://github.com/ailjushkin/robotframework-reportportal-ng
Author: Alexander Iljushkin
Author-email: ailjushkin@gmail.com
License: License :: OSI Approved :: Apache Software License
Keywords: testing,reporting,robot framework,reportportal
Platform: UNKNOWN
Classifier: Development Status :: 5 - Production/Stable
Classifier: Intended Audience :: Developers
Classifier: Topic :: Software Development :: Testing
Classifier: License :: OSI Approved :: Apache Software License
Classifier: Programming Language :: Python :: 3.6
Requires-Dist: reportportal-client (>=3.0.0)
Requires-Dist: robotframework (>=3.0.2)
